odoo/addons/crm_operating_unit/README.rst
odoo/addons/crm_operating_unit/__init__.py
odoo/addons/crm_operating_unit/__manifest__.py
odoo/addons/crm_operating_unit/models/__init__.py
odoo/addons/crm_operating_unit/models/crm_lead.py
odoo/addons/crm_operating_unit/readme/CONTRIBUTORS.rst
odoo/addons/crm_operating_unit/readme/DESCRIPTION.rst
odoo/addons/crm_operating_unit/readme/USAGE.rst
odoo/addons/crm_operating_unit/security/crm_security.xml
odoo/addons/crm_operating_unit/static/description/icon.png
odoo/addons/crm_operating_unit/static/description/index.html
odoo/addons/crm_operating_unit/tests/__init__.py
odoo/addons/crm_operating_unit/tests/test_crm_operating_unit.py
odoo/addons/crm_operating_unit/views/crm_lead_view.xml
odoo11_addon_crm_operating_unit-11.0.1.0.0.99.dev2.dist-info/METADATA
odoo11_addon_crm_operating_unit-11.0.1.0.0.99.dev2.dist-info/WHEEL
odoo11_addon_crm_operating_unit-11.0.1.0.0.99.dev2.dist-info/top_level.txt
odoo11_addon_crm_operating_unit-11.0.1.0.0.99.dev2.dist-info/RECORD
